jsonpath_cli/__init__.py
jsonpath_cli/_my_argument_parser.py
jsonpath_cli/main.py
jsonpath_cli-0.0.2.dev0.dist-info/LICENSE.md
jsonpath_cli-0.0.2.dev0.dist-info/METADATA
jsonpath_cli-0.0.2.dev0.dist-info/WHEEL
jsonpath_cli-0.0.2.dev0.dist-info/entry_points.txt
jsonpath_cli-0.0.2.dev0.dist-info/top_level.txt
jsonpath_cli-0.0.2.dev0.dist-info/zip-safe
jsonpath_cli-0.0.2.dev0.dist-info/RECORD
